pykg/__init__.py
knowledge_graph_client-0.0.4.dist-info/LICENSE
knowledge_graph_client-0.0.4.dist-info/METADATA
knowledge_graph_client-0.0.4.dist-info/WHEEL
knowledge_graph_client-0.0.4.dist-info/top_level.txt
knowledge_graph_client-0.0.4.dist-info/RECORD
