Metadata-Version: 2.1
Name: knowledge-graph-client
Version: 0.0.4
Summary: A simple Python client to a GraphQL Knowledge Graph
Home-page: https://pypi.org/project/knowledge-graph-client/
Author: Bart Meyers
Author-email: bart.meyers@flandersmake.be
License: UNKNOWN
Platform: UNKNOWN
Classifier: Programming Language :: Python :: 3
Classifier: License :: OSI Approved :: MIT License
Classifier: Operating System :: OS Independent
Requires-Python: >=3.6
License-File: LICENSE
